torchrua/__init__.py
torchrua/compose.py
torchrua/detach.py
torchrua/mask.py
torchrua/reduce.py
torchrua/segment.py
torchrua/utils.py
torchrua/core/__init__.py
torchrua/core/cast.py
torchrua/core/get.py
torchrua/core/set.py
torchrua/core/view.py
torchrua/layout/__init__.py
torchrua/layout/cat.py
torchrua/layout/left.py
torchrua/layout/pack.py
torchrua/layout/right.py
torchrua/select/__init__.py
torchrua/select/head.py
torchrua/select/last.py
torchrua/select/rev.py
torchrua/select/roll.py
torchrua/select/trunc.py
torchrua-0.5.1.dist-info/LICENSE
torchrua-0.5.1.dist-info/METADATA
torchrua-0.5.1.dist-info/WHEEL
torchrua-0.5.1.dist-info/top_level.txt
torchrua-0.5.1.dist-info/RECORD
